openapi_mcp/__init__.py
openapi_mcp/config_manager.py
kxj_openapi_mcp-0.1.3.dist-info/METADATA
kxj_openapi_mcp-0.1.3.dist-info/WHEEL
kxj_openapi_mcp-0.1.3.dist-info/entry_points.txt
kxj_openapi_mcp-0.1.3.dist-info/RECORD
