Metadata-Version: 2.4
Name: kxj-openapi-mcp
Version: 0.1.3
Summary: MCP OpenAPI Generator for Yii2 Controllers - 用于分析Yii2控制器并生成OpenAPI文档的MCP服务
Author-email: kouxujian1 <kouxujian@163.com>
Requires-Python: >=3.13
Requires-Dist: fastmcp>=0.1.0
Requires-Dist: httpx>=0.27.0
Requires-Dist: mcp[cli]>=1.9.3
Requires-Dist: pyyaml>=6.0
